{
  "id": "1310",
  "name": "流萤",
  "tag": "sam",
  "rarity": 5,
  "path": "毁灭",
  "path_key": "Warrior",
  "path_en": "Destruction",
  "element": "火",
  "element_key": "Fire",
  "max_sp": 240,
  "preview": "image/character_preview/1310.png",
  "portrait": "image/character_portrait/1310.png",
  "promotions": {
    "levels": [
      {
        "hp": 110.88,
        "hp_step": 5.544,
        "atk": 71.28,
        "atk_step": 3.564,
        "def_": 105.6,
        "def_step": 5.28,
        "spd": 104,
        "spd_step": 0,
        "taunt": 125,
        "taunt_step": 0,
        "crit_rate": 0.05,
        "crit_rate_step": 0,
        "crit_dmg": 0.5,
        "crit_dmg_step": 0
      },
      {
        "hp": 155.232,
        "hp_step": 5.544,
        "atk": 99.792,
        "atk_step": 3.564,
        "def_": 147.84,
        "def_step": 5.28,
        "spd": 104,
        "spd_step": 0,
        "taunt": 125,
        "taunt_step": 0,
        "crit_rate": 0.05,
        "crit_rate_step": 0,
        "crit_dmg": 0.5,
        "crit_dmg_step": 0
      },
      {
        "hp": 199.584,
        "hp_step": 5.544,
        "atk": 128.304,
        "atk_step": 3.564,
        "def_": 190.08,
        "def_step": 5.28,
        "spd": 104,
        "spd_step": 0,
        "taunt": 125,
        "taunt_step": 0,
        "crit_rate": 0.05,
        "crit_rate_step": 0,
        "crit_dmg": 0.5,
        "crit_dmg_step": 0
      },
      {
        "hp": 243.936,
        "hp_step": 5.544,
        "atk": 156.816,
        "atk_step": 3.564,
        "def_": 232.32,
        "def_step": 5.28,
        "spd": 104,
        "spd_step": 0,
        "taunt": 125,
        "taunt_step": 0,
        "crit_rate": 0.05,
        "crit_rate_step": 0,
        "crit_dmg": 0.5,
        "crit_dmg_step": 0
      },
      {
        "hp": 288.288,
        "hp_step": 5.544,
        "atk": 185.328,
        "atk_step": 3.564,
        "def_": 274.56,
        "def_step": 5.28,
        "spd": 104,
        "spd_step": 0,
        "taunt": 125,
        "taunt_step": 0,
        "crit_rate": 0.05,
        "crit_rate_step": 0,
        "crit_dmg": 0.5,
        "crit_dmg_step": 0
      },
      {
        "hp": 332.64,
        "hp_step": 5.544,
        "atk": 213.84,
        "atk_step": 3.564,
        "def_": 316.8,
        "def_step": 5.28,
        "spd": 104,
        "spd_step": 0,
        "taunt": 125,
        "taunt_step": 0,
        "crit_rate": 0.05,
        "crit_rate_step": 0,
        "crit_dmg": 0.5,
        "crit_dmg_step": 0
      },
      {
        "hp": 376.992,
        "hp_step": 5.544,
        "atk": 242.352,
        "atk_step": 3.564,
        "def_": 359.04,
        "def_step": 5.28,
        "spd": 104,
        "spd_step": 0,
        "taunt": 125,
        "taunt_step": 0,
        "crit_rate": 0.05,
        "crit_rate_step": 0,
        "crit_dmg": 0.5,
        "crit_dmg_step": 0
      }
    ],
    "materials": [
      [
        {
          "id": "2",
          "num": 4000
        },
        {
          "id": "114011",
          "num": 5
        }
      ],
      [
        {
          "id": "2",
          "num": 8000
        },
        {
          "id": "114011",
          "num": 10
        }
      ],
      [
        {
          "id": "2",
          "num": 16000
        },
        {
          "id": "114012",
          "num": 6
        },
        {
          "id": "110422",
          "num": 3
        }
      ],
      [
        {
          "id": "2",
          "num": 40000
        },
        {
          "id": "114012",
          "num": 9
        },
        {
          "id": "110422",
          "num": 7
        }
      ],
      [
        {
          "id": "2",
          "num": 80000
        },
        {
          "id": "114013",
          "num": 6
        },
        {
          "id": "110422",
          "num": 20
        }
      ],
      [
        {
          "id": "2",
          "num": 160000
        },
        {
          "id": "114013",
          "num": 9
        },
        {
          "id": "110422",
          "num": 35
        }
      ],
      []
    ]
  },
  "skills": [
    {
      "id": "131001",
      "name": "指令-闪燃推进",
      "type": "Normal",
      "type_text": "普攻",
      "effect": "SingleAttack",
      "effect_text": "单攻",
      "max_level": 10,
      "element": "Fire",
      "params": [
        [
          0.5
        ],
        [
          0.6
        ],
        [
          0.7
        ],
        [
          0.8
        ],
        [
          0.9
        ],
        [
          1
        ],
        [
          1.1
        ],
        [
          1.2
        ],
        [
          1.3
        ],
        [
          1.4
        ]
      ],
      "desc": "对指定敌方单体造成等同于装甲「萨姆」#1[i]%攻击力的火属性伤害。"
    },
    {
      "id": "131002",
      "name": "指令-天火轰击",
      "type": "BPSkill",
      "type_text": "战技",
      "effect": "SingleAttack",
      "effect_text": "单攻",
      "max_level": 15,
      "element": "Fire",
      "params": [
        [
          1,
          0.4,
          0.5,
          0.25
        ],
        [
          1.1,
          0.4,
          0.51,
          0.25
        ],
        [
          1.2,
          0.4,
          0.52,
          0.25
        ],
        [
          1.3,
          0.4,
          0.53,
          0.25
        ],
        [
          1.4,
          0.4,
          0.54,
          0.25
        ],
        [
          1.5,
          0.4,
          0.55,
          0.25
        ],
        [
          1.625,
          0.4,
          0.5625,
          0.25
        ],
        [
          1.75,
          0.4,
          0.575,
          0.25
        ],
        [
          1.875,
          0.4,
          0.5875,
          0.25
        ],
        [
          2,
          0.4,
          0.6,
          0.25
        ],
        [
          2.1,
          0.4,
          0.61,
          0.25
        ],
        [
          2.2,
          0.4,
          0.62,
          0.25
        ],
        [
          2.3,
          0.4,
          0.63,
          0.25
        ],
        [
          2.4,
          0.4,
          0.64,
          0.25
        ],
        [
          2.5,
          0.4,
          0.65,
          0.25
        ]
      ],
      "desc": "消耗等同于自身生命上限#2[i]%的生命值固定恢复等同于自身#3[i]%能量上限的能量，对指定敌方单体造成等同于装甲「萨姆」#1[i]%攻击力的火属性伤害。若当前生命值不足，施放战技时装甲「萨姆」的当前生命值降至1点。使自身下一次行动提前#4[i]%。"
    },
    {
      "id": "131003",
      "name": "火萤Ⅳ型-完全燃烧",
      "type": "Ultra",
      "type_text": "终结技",
      "effect": "Enhance",
      "effect_text": "强化",
      "max_level": 15,
      "element": "",
      "params": [
        [
          0.1,
          0.5,
          30,
          70
        ],
        [
          0.11,
          0.5,
          33,
          70
        ],
        [
          0.12,
          0.5,
          36,
          70
        ],
        [
          0.13,
          0.5,
          39,
          70
        ],
        [
          0.14,
          0.5,
          42,
          70
        ],
        [
          0.15,
          0.5,
          45,
          70
        ],
        [
          0.1625,
          0.5,
          48.75,
          70
        ],
        [
          0.175,
          0.5,
          52.5,
          70
        ],
        [
          0.1875,
          0.5,
          56.25,
          70
        ],
        [
          0.2,
          0.5,
          60,
          70
        ],
        [
          0.21,
          0.5,
          63,
          70
        ],
        [
          0.22,
          0.5,
          66,
          70
        ],
        [
          0.23,
          0.5,
          69,
          70
        ],
        [
          0.24,
          0.5,
          72,
          70
        ],
        [
          0.25,
          0.5,
          75,
          70
        ]
      ],
      "desc": "进入「完全燃烧」状态，自身行动提前100%并获得强化普攻和强化战技。「完全燃烧」状态下速度提高#3[i]点，且施放强化普攻、强化战技时自身弱点击破效率提高#2[i]%、使敌方目标受到装甲「萨姆」造成的击破伤害提高#1[f1]%，持续至本次攻击结束。\n行动序列上出现「完全燃烧」倒计时，倒计时回合开始时装甲「萨姆」解除「完全燃烧」状态，倒计时固定拥有#4[i]速度。\n「完全燃烧」状态下装甲「萨姆」无法施放终结技。"
    },
    {
      "id": "131004",
      "name": "茧式源火中枢",
      "type": "Talent",
      "type_text": "天赋",
      "effect": "Defence",
      "effect_text": "防御",
      "max_level": 15,
      "element": "Fire",
      "params": [
        [
          0.2,
          0.5,
          0.2,
          0.1
        ],
        [
          0.22,
          0.5,
          0.2,
          0.12
        ],
        [
          0.24,
          0.5,
          0.2,
          0.14
        ],
        [
          0.26,
          0.5,
          0.2,
          0.16
        ],
        [
          0.28,
          0.5,
          0.2,
          0.18
        ],
        [
          0.3,
          0.5,
          0.2,
          0.2
        ],
        [
          0.325,
          0.5,
          0.2,
          0.225
        ],
        [
          0.35,
          0.5,
          0.2,
          0.25
        ],
        [
          0.375,
          0.5,
          0.2,
          0.275
        ],
        [
          0.4,
          0.5,
          0.2,
          0.3
        ],
        [
          0.42,
          0.5,
          0.2,
          0.32
        ],
        [
          0.44,
          0.5,
          0.2,
          0.34
        ],
        [
          0.46,
          0.5,
          0.2,
          0.36
        ],
        [
          0.48,
          0.5,
          0.2,
          0.38
        ],
        [
          0.5,
          0.5,
          0.2,
          0.4
        ]
      ],
      "desc": "生命值越低受到的伤害越低，生命值小于等于#3[i]%时减伤效果达到最大值，最多降低#1[i]%。「完全燃烧」状态下减伤效果维持最大值，效果抵抗提高#4[i]%。\n战斗开始时若能量不足#2[i]%则使其恢复至#2[i]%。当能量恢复至上限时解除自身所有负面效果。"
    },
    {
      "id": "131006",
      "name": "攻击",
      "type": "MazeNormal",
      "type_text": "dev_连携",
      "effect": "MazeAttack",
      "effect_text": "",
      "max_level": 1,
      "element": "Fire",
      "params": [],
      "desc": "攻击敌人，进入战斗后削弱敌方目标对应属性韧性。"
    },
    {
      "id": "131007",
      "name": "Δ指令-焦土陨击",
      "type": "Maze",
      "type_text": "秘技",
      "effect": "MazeAttack",
      "effect_text": "",
      "max_level": 1,
      "element": "Fire",
      "params": [
        [
          5,
          2,
          2
        ]
      ],
      "desc": "跳跃至空中并进行自由移动，持续#1[i]秒，此时施放下落攻击可以提前结束持续时间。持续时间结束后，下落并立即攻击一定范围内的所有敌人，每个波次开始时为敌方全体添加火属性弱点，持续#3[i]回合，此后对敌方全体造成等同于装甲「萨姆」#2[i]%攻击力的火属性伤害。"
    },
    {
      "id": "131008",
      "name": "火萤Ⅳ型-底火斩击",
      "type": "Normal",
      "type_text": "普攻",
      "effect": "SingleAttack",
      "effect_text": "单攻",
      "max_level": 10,
      "element": "Fire",
      "params": [
        [
          1,
          0.2
        ],
        [
          1.2,
          0.2
        ],
        [
          1.4,
          0.2
        ],
        [
          1.6,
          0.2
        ],
        [
          1.8,
          0.2
        ],
        [
          2,
          0.2
        ],
        [
          2.2,
          0.2
        ],
        [
          2.4,
          0.2
        ],
        [
          2.6,
          0.2
        ],
        [
          2.8,
          0.2
        ]
      ],
      "desc": "回复等同于自身#2[i]%生命上限的生命值。对指定敌方单体造成等同于装甲「萨姆」#1[i]%攻击力的火属性伤害。"
    },
    {
      "id": "131009",
      "name": "火萤Ⅳ型-死星过载",
      "type": "BPSkill",
      "type_text": "战技",
      "effect": "Blast",
      "effect_text": "扩散",
      "max_level": 15,
      "element": "Fire",
      "params": [
        [
          1,
          0.5,
          0.25,
          2,
          0.2,
          0.1,
          3.6
        ],
        [
          1.1,
          0.55,
          0.25,
          2,
          0.2,
          0.1,
          3.6
        ],
        [
          1.2,
          0.6,
          0.25,
          2,
          0.2,
          0.1,
          3.6
        ],
        [
          1.3,
          0.65,
          0.25,
          2,
          0.2,
          0.1,
          3.6
        ],
        [
          1.4,
          0.7,
          0.25,
          2,
          0.2,
          0.1,
          3.6
        ],
        [
          1.5,
          0.75,
          0.25,
          2,
          0.2,
          0.1,
          3.6
        ],
        [
          1.625,
          0.8125,
          0.25,
          2,
          0.2,
          0.1,
          3.6
        ],
        [
          1.75,
          0.875,
          0.25,
          2,
          0.2,
          0.1,
          3.6
        ],
        [
          1.875,
          0.9375,
          0.25,
          2,
          0.2,
          0.1,
          3.6
        ],
        [
          2,
          1,
          0.25,
          2,
          0.2,
          0.1,
          3.6
        ],
        [
          2.1,
          1.05,
          0.25,
          2,
          0.2,
          0.1,
          3.6
        ],
        [
          2.2,
          1.1,
          0.25,
          2,
          0.2,
          0.1,
          3.6
        ],
        [
          2.3,
          1.15,
          0.25,
          2,
          0.2,
          0.1,
          3.6
        ],
        [
          2.4,
          1.2,
          0.25,
          2,
          0.2,
          0.1,
          3.6
        ],
        [
          2.5,
          1.25,
          0.25,
          2,
          0.2,
          0.1,
          3.6
        ]
      ],
      "desc": "回复等同于自身#3[i]%生命上限的生命值。为指定敌方单体添加火属性弱点，持续#4[i]回合。对该目标造成等同于装甲「萨姆」（#5[f1]*击破特攻+#1[f1]%）攻击力的火属性伤害。同时对其相邻目标造成等同于装甲「萨姆」（#6[f1]*击破特攻+#2[f1]%）攻击力的火属性伤害。最多计算#7[i]%击破特攻。"
    },
    {
      "id": "1131001",
      "name": "指令-闪燃推进",
      "type": "Normal",
      "type_text": "普攻",
      "effect": "SingleAttack",
      "effect_text": "单攻",
      "max_level": 10,
      "element": "Fire",
      "params": [
        [
          0.5
        ],
        [
          0.6
        ],
        [
          0.7
        ],
        [
          0.8
        ],
        [
          0.9
        ],
        [
          1
        ],
        [
          1.1
        ],
        [
          1.2
        ],
        [
          1.3
        ],
        [
          1.4
        ]
      ],
      "desc": "对指定敌方单体造成等同于装甲「萨姆」#1[i]%攻击力的火属性伤害。"
    },
    {
      "id": "1131002",
      "name": "指令-天火轰击",
      "type": "BPSkill",
      "type_text": "战技",
      "effect": "SingleAttack",
      "effect_text": "单攻",
      "max_level": 15,
      "element": "Fire",
      "params": [
        [
          1,
          0.4,
          0.5,
          0.25
        ],
        [
          1.1,
          0.4,
          0.51,
          0.25
        ],
        [
          1.2,
          0.4,
          0.52,
          0.25
        ],
        [
          1.3,
          0.4,
          0.53,
          0.25
        ],
        [
          1.4,
          0.4,
          0.54,
          0.25
        ],
        [
          1.5,
          0.4,
          0.55,
          0.25
        ],
        [
          1.625,
          0.4,
          0.5625,
          0.25
        ],
        [
          1.75,
          0.4,
          0.575,
          0.25
        ],
        [
          1.875,
          0.4,
          0.5875,
          0.25
        ],
        [
          2,
          0.4,
          0.6,
          0.25
        ],
        [
          2.1,
          0.4,
          0.61,
          0.25
        ],
        [
          2.2,
          0.4,
          0.62,
          0.25
        ],
        [
          2.3,
          0.4,
          0.63,
          0.25
        ],
        [
          2.4,
          0.4,
          0.64,
          0.25
        ],
        [
          2.5,
          0.4,
          0.65,
          0.25
        ]
      ],
      "desc": "消耗等同于自身生命上限#2[i]%的生命值固定恢复等同于自身#3[i]%能量上限的能量，对指定敌方单体造成等同于装甲「萨姆」#1[i]%攻击力的火属性伤害。若当前生命值不足，施放战技时装甲「萨姆」的当前生命值降至1点。使自身下一次行动提前#4[i]%。"
    },
    {
      "id": "1131003",
      "name": "火萤Ⅳ型-完全燃烧",
      "type": "Ultra",
      "type_text": "终结技",
      "effect": "Enhance",
      "effect_text": "强化",
      "max_level": 15,
      "element": "",
      "params": [
        [
          0.1,
          0.5,
          30,
          70
        ],
        [
          0.11,
          0.5,
          33,
          70
        ],
        [
          0.12,
          0.5,
          36,
          70
        ],
        [
          0.13,
          0.5,
          39,
          70
        ],
        [
          0.14,
          0.5,
          42,
          70
        ],
        [
          0.15,
          0.5,
          45,
          70
        ],
        [
          0.1625,
          0.5,
          48.75,
          70
        ],
        [
          0.175,
          0.5,
          52.5,
          70
        ],
        [
          0.1875,
          0.5,
          56.25,
          70
        ],
        [
          0.2,
          0.5,
          60,
          70
        ],
        [
          0.21,
          0.5,
          63,
          70
        ],
        [
          0.22,
          0.5,
          66,
          70
        ],
        [
          0.23,
          0.5,
          69,
          70
        ],
        [
          0.24,
          0.5,
          72,
          70
        ],
        [
          0.25,
          0.5,
          75,
          70
        ]
      ],
      "desc": "进入「完全燃烧」状态，自身行动提前100%并获得强化普攻和强化战技。「完全燃烧」状态下速度提高#3[i]点，且施放强化普攻、强化战技时自身弱点击破效率提高#2[i]%、使敌方目标受到装甲「萨姆」造成的击破伤害提高#1[f1]%，持续至本次攻击结束。\n行动序列上出现「完全燃烧」倒计时，倒计时回合开始时装甲「萨姆」解除「完全燃烧」状态，倒计时固定拥有#4[i]速度。\n「完全燃烧」状态下装甲「萨姆」无法施放终结技。"
    },
    {
      "id": "1131004",
      "name": "茧式源火中枢",
      "type": "Talent",
      "type_text": "天赋",
      "effect": "Defence",
      "effect_text": "防御",
      "max_level": 15,
      "element": "Fire",
      "params": [
        [
          0.2,
          0.5,
          0.2,
          0.1
        ],
        [
          0.22,
          0.5,
          0.2,
          0.12
        ],
        [
          0.24,
          0.5,
          0.2,
          0.14
        ],
        [
          0.26,
          0.5,
          0.2,
          0.16
        ],
        [
          0.28,
          0.5,
          0.2,
          0.18
        ],
        [
          0.3,
          0.5,
          0.2,
          0.2
        ],
        [
          0.325,
          0.5,
          0.2,
          0.225
        ],
        [
          0.35,
          0.5,
          0.2,
          0.25
        ],
        [
          0.375,
          0.5,
          0.2,
          0.275
        ],
        [
          0.4,
          0.5,
          0.2,
          0.3
        ],
        [
          0.42,
          0.5,
          0.2,
          0.32
        ],
        [
          0.44,
          0.5,
          0.2,
          0.34
        ],
        [
          0.46,
          0.5,
          0.2,
          0.36
        ],
        [
          0.48,
          0.5,
          0.2,
          0.38
        ],
        [
          0.5,
          0.5,
          0.2,
          0.4
        ]
      ],
      "desc": "生命值越低受到的伤害越低，生命值小于等于#3[i]%时减伤效果达到最大值，最多降低#1[i]%。「完全燃烧」状态下减伤效果维持最大值，效果抵抗提高#4[i]%。\n战斗开始时若能量不足#2[i]%则使其恢复至#2[i]%。当能量恢复至上限时解除自身所有负面效果。"
    },
    {
      "id": "1131006",
      "name": "攻击",
      "type": "MazeNormal",
      "type_text": "dev_连携",
      "effect": "MazeAttack",
      "effect_text": "",
      "max_level": 1,
      "element": "Fire",
      "params": [],
      "desc": "攻击敌人，进入战斗后削弱敌方目标对应属性韧性。"
    },
    {
      "id": "1131007",
      "name": "Δ指令-焦土陨击",
      "type": "Maze",
      "type_text": "秘技",
      "effect": "MazeAttack",
      "effect_text": "",
      "max_level": 1,
      "element": "Fire",
      "params": [
        [
          5,
          2,
          2
        ]
      ],
      "desc": "跳跃至空中并进行自由移动，持续#1[i]秒，此时施放下落攻击可以提前结束持续时间。持续时间结束后，下落并立即攻击一定范围内的所有敌人，每个波次开始时为敌方全体添加火属性弱点，持续#3[i]回合，此后对敌方全体造成等同于装甲「萨姆」#2[i]%攻击力的火属性伤害。"
    },
    {
      "id": "1131008",
      "name": "火萤Ⅳ型-底火斩击",
      "type": "Normal",
      "type_text": "普攻",
      "effect": "SingleAttack",
      "effect_text": "单攻",
      "max_level": 10,
      "element": "Fire",
      "params": [
        [
          1,
          0.2
        ],
        [
          1.2,
          0.2
        ],
        [
          1.4,
          0.2
        ],
        [
          1.6,
          0.2
        ],
        [
          1.8,
          0.2
        ],
        [
          2,
          0.2
        ],
        [
          2.2,
          0.2
        ],
        [
          2.4,
          0.2
        ],
        [
          2.6,
          0.2
        ],
        [
          2.8,
          0.2
        ]
      ],
      "desc": "回复等同于自身#2[i]%生命上限的生命值。对指定敌方单体造成等同于装甲「萨姆」#1[i]%攻击力的火属性伤害。"
    },
    {
      "id": "1131009",
      "name": "火萤Ⅳ型-死星过载",
      "type": "BPSkill",
      "type_text": "战技",
      "effect": "Blast",
      "effect_text": "扩散",
      "max_level": 15,
      "element": "Fire",
      "params": [
        [
          1,
          0.5,
          0,
          0,
          0.2,
          0.1,
          3.6,
          0
        ],
        [
          1.1,
          0.55,
          0,
          0,
          0.2,
          0.1,
          3.6,
          0
        ],
        [
          1.2,
          0.6,
          0,
          0,
          0.2,
          0.1,
          3.6,
          0
        ],
        [
          1.3,
          0.65,
          0,
          0,
          0.2,
          0.1,
          3.6,
          0
        ],
        [
          1.4,
          0.7,
          0,
          0,
          0.2,
          0.1,
          3.6,
          0
        ],
        [
          1.5,
          0.75,
          0,
          0,
          0.2,
          0.1,
          3.6,
          0
        ],
        [
          1.625,
          0.8125,
          0,
          0,
          0.2,
          0.1,
          3.6,
          0
        ],
        [
          1.75,
          0.875,
          0,
          0,
          0.2,
          0.1,
          3.6,
          0
        ],
        [
          1.875,
          0.9375,
          0,
          0,
          0.2,
          0.1,
          3.6,
          0
        ],
        [
          2,
          1,
          0,
          0,
          0.2,
          0.1,
          3.6,
          0
        ],
        [
          2.1,
          1.05,
          0,
          0,
          0.2,
          0.1,
          3.6,
          0
        ],
        [
          2.2,
          1.1,
          0,
          0,
          0.2,
          0.1,
          3.6,
          0
        ],
        [
          2.3,
          1.15,
          0,
          0,
          0.2,
          0.1,
          3.6,
          0
        ],
        [
          2.4,
          1.2,
          0,
          0,
          0.2,
          0.1,
          3.6,
          0
        ],
        [
          2.5,
          1.25,
          0,
          0,
          0.2,
          0.1,
          3.6,
          0
        ]
      ],
      "desc": "回复等同于自身25%生命上限的生命值。为指定敌方单体及其相邻目标添加火属性弱点，持续2回合。对该目标造成等同于装甲「萨姆」（#5[f1]*击破特攻+#1[f1]%）攻击力的火属性伤害。同时对其相邻目标造成等同于装甲「萨姆」（#6[f1]*击破特攻+#2[f1]%）攻击力的火属性伤害。最多计算#7[i]%击破特攻。"
    }
  ],
  "traces": {
    "skill_upgrades": [
      {
        "id": "1310001",
        "name": "",
        "desc": "",
        "anchor": "Point01",
        "pre_points": [],
        "level_up_skills": [
          {
            "id": "131001",
            "num": 1
          },
          {
            "id": "131008",
            "num": 1
          }
        ],
        "levels": [
          {
            "promotion": 0,
            "level": 0,
            "properties": [],
            "materials": []
          },
          {
            "promotion": 2,
            "level": 0,
            "properties": [],
            "materials": [
              {
                "id": "2",
                "num": 5000
              },
              {
                "id": "110181",
                "num": 3
              },
              {
                "id": "114011",
                "num": 6
              }
            ]
          },
          {
            "promotion": 3,
            "level": 0,
            "properties": [],
            "materials": [
              {
                "id": "2",
                "num": 10000
              },
              {
                "id": "110182",
                "num": 3
              },
              {
                "id": "114012",
                "num": 3
              }
            ]
          },
          {
            "promotion": 4,
            "level": 0,
            "properties": [],
            "materials": [
              {
                "id": "2",
                "num": 20000
              },
              {
                "id": "110182",
                "num": 5
              },
              {
                "id": "114012",
                "num": 4
              }
            ]
          },
          {
            "promotion": 5,
            "level": 0,
            "properties": [],
            "materials": [
              {
                "id": "2",
                "num": 45000
              },
              {
                "id": "110183",
                "num": 3
              },
              {
                "id": "114013",
                "num": 3
              }
            ]
          },
          {
            "promotion": 6,
            "level": 0,
            "properties": [],
            "materials": [
              {
                "id": "2",
                "num": 160000
              },
              {
                "id": "110183",
                "num": 8
              },
              {
                "id": "114013",
                "num": 4
              }
            ]
          }
        ]
      },
      {
        "id": "1310002",
        "name": "",
        "desc": "",
        "anchor": "Point02",
        "pre_points": [],
        "level_up_skills": [
          {
            "id": "131002",
            "num": 1
          },
          {
            "id": "131009",
            "num": 1
          }
        ],
        "levels": [
          {
            "promotion": 0,
            "level": 0,
            "properties": [],
            "materials": []
          },
          {
            "promotion": 1,
            "level": 0,
            "properties": [],
            "materials": [
              {
                "id": "2",
                "num": 2500
              },
              {
                "id": "114011",
                "num": 3
              }
            ]
          },
          {
            "promotion": 2,
            "level": 0,
            "properties": [],
            "materials": [
              {
                "id": "2",
                "num": 5000
              },
              {
                "id": "110181",
                "num": 3
              },
              {
                "id": "114011",
                "num": 6
              }
            ]
          },
          {
            "promotion": 3,
            "level": 0,
            "properties": [],
            "materials": [
              {
                "id": "2",
                "num": 10000
              },
              {
                "id": "110182",
                "num": 3
              },
              {
                "id": "114012",
                "num": 3
              }
            ]
          },
          {
            "promotion": 4,
            "level": 0,
            "properties": [],
            "materials": [
              {
                "id": "2",
                "num": 20000
              },
              {
                "id": "110182",
                "num": 5
              },
              {
                "id": "114012",
                "num": 4
              }
            ]
          },
          {
            "promotion": 4,
            "level": 0,
            "properties": [],
            "materials": [
              {
                "id": "2",
                "num": 30000
              },
              {
                "id": "110182",
                "num": 7
              },
              {
                "id": "114012",
                "num": 6
              }
            ]
          },
          {
            "promotion": 5,
            "level": 0,
            "properties": [],
            "materials": [
              {
                "id": "2",
                "num": 45000
              },
              {
                "id": "110183",
                "num": 3
              },
              {
                "id": "114013",
                "num": 3
              }
            ]
          },
          {
            "promotion": 5,
            "level": 0,
            "properties": [],
            "materials": [
              {
                "id": "2",
                "num": 80000
              },
              {
                "id": "110183",
                "num": 5
              },
              {
                "id": "110505",
                "num": 1
              },
              {
                "id": "114013",
                "num": 4
              }
            ]
          },
          {
            "promotion": 6,
            "level": 0,
            "properties": [],
            "materials": [
              {
                "id": "2",
                "num": 160000
              },
              {
                "id": "110183",
                "num": 8
              },
              {
                "id": "241",
                "num": 1
              },
              {
                "id": "110505",
                "num": 1
              }
            ]
          },
          {
            "promotion": 6,
            "level": 0,
            "properties": [],
            "materials": [
              {
                "id": "2",
                "num": 300000
              },
              {
                "id": "110183",
                "num": 14
              },
              {
                "id": "241",
                "num": 1
              },
              {
                "id": "110505",
                "num": 1
              }
            ]
          }
        ]
      },
      {
        "id": "1310003",
        "name": "",
        "desc": "",
        "anchor": "Point03",
        "pre_points": [],
        "level_up_skills": [
          {
            "id": "131003",
            "num": 1
          }
        ],
        "levels": [
          {
            "promotion": 0,
            "level": 0,
            "properties": [],
            "materials": []
          },
          {
            "promotion": 1,
            "level": 0,
            "properties": [],
            "materials": [
              {
                "id": "2",
                "num": 2500
              },
              {
                "id": "114011",
                "num": 3
              }
            ]
          },
          {
            "promotion": 2,
            "level": 0,
            "properties": [],
            "materials": [
              {
                "id": "2",
                "num": 5000
              },
              {
                "id": "110181",
                "num": 3
              },
              {
                "id": "114011",
                "num": 6
              }
            ]
          },
          {
            "promotion": 3,
            "level": 0,
            "properties": [],
            "materials": [
              {
                "id": "2",
                "num": 10000
              },
              {
                "id": "110182",
                "num": 3
              },
              {
                "id": "114012",
                "num": 3
              }
            ]
          },
          {
            "promotion": 4,
            "level": 0,
            "properties": [],
            "materials": [
              {
                "id": "2",
                "num": 20000
              },
              {
                "id": "110182",
                "num": 5
              },
              {
                "id": "114012",
                "num": 4
              }
            ]
          },
          {
            "promotion": 4,
            "level": 0,
            "properties": [],
            "materials": [
              {
                "id": "2",
                "num": 30000
              },
              {
                "id": "110182",
                "num": 7
              },
              {
                "id": "114012",
                "num": 6
              }
            ]
          },
          {
            "promotion": 5,
            "level": 0,
            "properties": [],
            "materials": [
              {
                "id": "2",
                "num": 45000
              },
              {
                "id": "110183",
                "num": 3
              },
              {
                "id": "114013",
                "num": 3
              }
            ]
          },
          {
            "promotion": 5,
            "level": 0,
            "properties": [],
            "materials": [
              {
                "id": "2",
                "num": 80000
              },
              {
                "id": "110183",
                "num": 5
              },
              {
                "id": "110505",
                "num": 1
              },
              {
                "id": "114013",
                "num": 4
              }
            ]
          },
          {
            "promotion": 6,
            "level": 0,
            "properties": [],
            "materials": [
              {
                "id": "2",
                "num": 160000
              },
              {
                "id": "110183",
                "num": 8
              },
              {
                "id": "241",
                "num": 1
              },
              {
                "id": "110505",
                "num": 1
              }
            ]
          },
          {
            "promotion": 6,
            "level": 0,
            "properties": [],
            "materials": [
              {
                "id": "2",
                "num": 300000
              },
              {
                "id": "110183",
                "num": 14
              },
              {
                "id": "241",
                "num": 1
              },
              {
                "id": "110505",
                "num": 1
              }
            ]
          }
        ]
      },
      {
        "id": "1310004",
        "name": "",
        "desc": "",
        "anchor": "Point04",
        "pre_points": [],
        "level_up_skills": [
          {
            "id": "131004",
            "num": 1
          }
        ],
        "levels": [
          {
            "promotion": 0,
            "level": 0,
            "properties": [],
            "materials": []
          },
          {
            "promotion": 1,
            "level": 0,
            "properties": [],
            "materials": [
              {
                "id": "2",
                "num": 2500
              },
              {
                "id": "114011",
                "num": 3
              }
            ]
          },
          {
            "promotion": 2,
            "level": 0,
            "properties": [],
            "materials": [
              {
                "id": "2",
                "num": 5000
              },
              {
                "id": "110181",
                "num": 3
              },
              {
                "id": "114011",
                "num": 6
              }
            ]
          },
          {
            "promotion": 3,
            "level": 0,
            "properties": [],
            "materials": [
              {
                "id": "2",
                "num": 10000
              },
              {
                "id": "110182",
                "num": 3
              },
              {
                "id": "114012",
                "num": 3
              }
            ]
          },
          {
            "promotion": 4,
            "level": 0,
            "properties": [],
            "materials": [
              {
                "id": "2",
                "num": 20000
              },
              {
                "id": "110182",
                "num": 5
              },
              {
                "id": "114012",
                "num": 4
              }
            ]
          },
          {
            "promotion": 4,
            "level": 0,
            "properties": [],
            "materials": [
              {
                "id": "2",
                "num": 30000
              },
              {
                "id": "110182",
                "num": 7
              },
              {
                "id": "114012",
                "num": 6
              }
            ]
          },
          {
            "promotion": 5,
            "level": 0,
            "properties": [],
            "materials": [
              {
                "id": "2",
                "num": 45000
              },
              {
                "id": "110183",
                "num": 3
              },
              {
                "id": "114013",
                "num": 3
              }
            ]
          },
          {
            "promotion": 5,
            "level": 0,
            "properties": [],
            "materials": [
              {
                "id": "2",
                "num": 80000
              },
              {
                "id": "110183",
                "num": 5
              },
              {
                "id": "110505",
                "num": 1
              },
              {
                "id": "114013",
                "num": 4
              }
            ]
          },
          {
            "promotion": 6,
            "level": 0,
            "properties": [],
            "materials": [
              {
                "id": "2",
                "num": 160000
              },
              {
                "id": "110183",
                "num": 8
              },
              {
                "id": "241",
                "num": 1
              },
              {
                "id": "110505",
                "num": 1
              }
            ]
          },
          {
            "promotion": 6,
            "level": 0,
            "properties": [],
            "materials": [
              {
                "id": "2",
                "num": 300000
              },
              {
                "id": "110183",
                "num": 14
              },
              {
                "id": "241",
                "num": 1
              },
              {
                "id": "110505",
                "num": 1
              }
            ]
          }
        ]
      },
      {
        "id": "1310007",
        "name": "",
        "desc": "",
        "anchor": "Point05",
        "pre_points": [],
        "level_up_skills": [
          {
            "id": "131007",
            "num": 1
          }
        ],
        "levels": [
          {
            "promotion": 0,
            "level": 0,
            "properties": [],
            "materials": []
          }
        ]
      },
      {
        "id": "11310001",
        "name": "",
        "desc": "",
        "anchor": "Point01",
        "pre_points": [],
        "level_up_skills": [
          {
            "id": "1131001",
            "num": 1
          },
          {
            "id": "1131008",
            "num": 1
          }
        ],
        "levels": [
          {
            "promotion": 0,
            "level": 0,
            "properties": [],
            "materials": []
          },
          {
            "promotion": 2,
            "level": 0,
            "properties": [],
            "materials": [
              {
                "id": "2",
                "num": 5000
              },
              {
                "id": "110181",
                "num": 3
              },
              {
                "id": "114011",
                "num": 6
              }
            ]
          },
          {
            "promotion": 3,
            "level": 0,
            "properties": [],
            "materials": [
              {
                "id": "2",
                "num": 10000
              },
              {
                "id": "110182",
                "num": 3
              },
              {
                "id": "114012",
                "num": 3
              }
            ]
          },
          {
            "promotion": 4,
            "level": 0,
            "properties": [],
            "materials": [
              {
                "id": "2",
                "num": 20000
              },
              {
                "id": "110182",
                "num": 5
              },
              {
                "id": "114012",
                "num": 4
              }
            ]
          },
          {
            "promotion": 5,
            "level": 0,
            "properties": [],
            "materials": [
              {
                "id": "2",
                "num": 45000
              },
              {
                "id": "110183",
                "num": 3
              },
              {
                "id": "114013",
                "num": 3
              }
            ]
          },
          {
            "promotion": 6,
            "level": 0,
            "properties": [],
            "materials": [
              {
                "id": "2",
                "num": 160000
              },
              {
                "id": "110183",
                "num": 8
              },
              {
                "id": "114013",
                "num": 4
              }
            ]
          }
        ]
      },
      {
        "id": "11310002",
        "name": "",
        "desc": "",
        "anchor": "Point02",
        "pre_points": [],
        "level_up_skills": [
          {
            "id": "1131002",
            "num": 1
          },
          {
            "id": "1131009",
            "num": 1
          }
        ],
        "levels": [
          {
            "promotion": 0,
            "level": 0,
            "properties": [],
            "materials": []
          },
          {
            "promotion": 1,
            "level": 0,
            "properties": [],
            "materials": [
              {
                "id": "2",
                "num": 2500
              },
              {
                "id": "114011",
                "num": 3
              }
            ]
          },
          {
            "promotion": 2,
            "level": 0,
            "properties": [],
            "materials": [
              {
                "id": "2",
                "num": 5000
              },
              {
                "id": "110181",
                "num": 3
              },
              {
                "id": "114011",
                "num": 6
              }
            ]
          },
          {
            "promotion": 3,
            "level": 0,
            "properties": [],
            "materials": [
              {
                "id": "2",
                "num": 10000
              },
              {
                "id": "110182",
                "num": 3
              },
              {
                "id": "114012",
                "num": 3
              }
            ]
          },
          {
            "promotion": 4,
            "level": 0,
            "properties": [],
            "materials": [
              {
                "id": "2",
                "num": 20000
              },
              {
                "id": "110182",
                "num": 5
              },
              {
                "id": "114012",
                "num": 4
              }
            ]
          },
          {
            "promotion": 4,
            "level": 0,
            "properties": [],
            "materials": [
              {
                "id": "2",
                "num": 30000
              },
              {
                "id": "110182",
                "num": 7
              },
              {
                "id": "114012",
                "num": 6
              }
            ]
          },
          {
            "promotion": 5,
            "level": 0,
            "properties": [],
            "materials": [
              {
                "id": "2",
                "num": 45000
              },
              {
                "id": "110183",
                "num": 3
              },
              {
                "id": "114013",
                "num": 3
              }
            ]
          },
          {
            "promotion": 5,
            "level": 0,
            "properties": [],
            "materials": [
              {
                "id": "2",
                "num": 80000
              },
              {
                "id": "110183",
                "num": 5
              },
              {
                "id": "110505",
                "num": 1
              },
              {
                "id": "114013",
                "num": 4
              }
            ]
          },
          {
            "promotion": 6,
            "level": 0,
            "properties": [],
            "materials": [
              {
                "id": "2",
                "num": 160000
              },
              {
                "id": "110183",
                "num": 8
              },
              {
                "id": "241",
                "num": 1
              },
              {
                "id": "110505",
                "num": 1
              }
            ]
          },
          {
            "promotion": 6,
            "level": 0,
            "properties": [],
            "materials": [
              {
                "id": "2",
                "num": 300000
              },
              {
                "id": "110183",
                "num": 14
              },
              {
                "id": "241",
                "num": 1
              },
              {
                "id": "110505",
                "num": 1
              }
            ]
          }
        ]
      },
      {
        "id": "11310003",
        "name": "",
        "desc": "",
        "anchor": "Point03",
        "pre_points": [],
        "level_up_skills": [
          {
            "id": "1131003",
            "num": 1
          }
        ],
        "levels": [
          {
            "promotion": 0,
            "level": 0,
            "properties": [],
            "materials": []
          },
          {
            "promotion": 1,
            "level": 0,
            "properties": [],
            "materials": [
              {
                "id": "2",
                "num": 2500
              },
              {
                "id": "114011",
                "num": 3
              }
            ]
          },
          {
            "promotion": 2,
            "level": 0,
            "properties": [],
            "materials": [
              {
                "id": "2",
                "num": 5000
              },
              {
                "id": "110181",
                "num": 3
              },
              {
                "id": "114011",
                "num": 6
              }
            ]
          },
          {
            "promotion": 3,
            "level": 0,
            "properties": [],
            "materials": [
              {
                "id": "2",
                "num": 10000
              },
              {
                "id": "110182",
                "num": 3
              },
              {
                "id": "114012",
                "num": 3
              }
            ]
          },
          {
            "promotion": 4,
            "level": 0,
            "properties": [],
            "materials": [
              {
                "id": "2",
                "num": 20000
              },
              {
                "id": "110182",
                "num": 5
              },
              {
                "id": "114012",
                "num": 4
              }
            ]
          },
          {
            "promotion": 4,
            "level": 0,
            "properties": [],
            "materials": [
              {
                "id": "2",
                "num": 30000
              },
              {
                "id": "110182",
                "num": 7
              },
              {
                "id": "114012",
                "num": 6
              }
            ]
          },
          {
            "promotion": 5,
            "level": 0,
            "properties": [],
            "materials": [
              {
                "id": "2",
                "num": 45000
              },
              {
                "id": "110183",
                "num": 3
              },
              {
                "id": "114013",
                "num": 3
              }
            ]
          },
          {
            "promotion": 5,
            "level": 0,
            "properties": [],
            "materials": [
              {
                "id": "2",
                "num": 80000
              },
              {
                "id": "110183",
                "num": 5
              },
              {
                "id": "110505",
                "num": 1
              },
              {
                "id": "114013",
                "num": 4
              }
            ]
          },
          {
            "promotion": 6,
            "level": 0,
            "properties": [],
            "materials": [
              {
                "id": "2",
                "num": 160000
              },
              {
                "id": "110183",
                "num": 8
              },
              {
                "id": "241",
                "num": 1
              },
              {
                "id": "110505",
                "num": 1
              }
            ]
          },
          {
            "promotion": 6,
            "level": 0,
            "properties": [],
            "materials": [
              {
                "id": "2",
                "num": 300000
              },
              {
                "id": "110183",
                "num": 14
              },
              {
                "id": "241",
                "num": 1
              },
              {
                "id": "110505",
                "num": 1
              }
            ]
          }
        ]
      },
      {
        "id": "11310004",
        "name": "",
        "desc": "",
        "anchor": "Point04",
        "pre_points": [],
        "level_up_skills": [
          {
            "id": "1131004",
            "num": 1
          }
        ],
        "levels": [
          {
            "promotion": 0,
            "level": 0,
            "properties": [],
            "materials": []
          },
          {
            "promotion": 1,
            "level": 0,
            "properties": [],
            "materials": [
              {
                "id": "2",
                "num": 2500
              },
              {
                "id": "114011",
                "num": 3
              }
            ]
          },
          {
            "promotion": 2,
            "level": 0,
            "properties": [],
            "materials": [
              {
                "id": "2",
                "num": 5000
              },
              {
                "id": "110181",
                "num": 3
              },
              {
                "id": "114011",
                "num": 6
              }
            ]
          },
          {
            "promotion": 3,
            "level": 0,
            "properties": [],
            "materials": [
              {
                "id": "2",
                "num": 10000
              },
              {
                "id": "110182",
                "num": 3
              },
              {
                "id": "114012",
                "num": 3
              }
            ]
          },
          {
            "promotion": 4,
            "level": 0,
            "properties": [],
            "materials": [
              {
                "id": "2",
                "num": 20000
              },
              {
                "id": "110182",
                "num": 5
              },
              {
                "id": "114012",
                "num": 4
              }
            ]
          },
          {
            "promotion": 4,
            "level": 0,
            "properties": [],
            "materials": [
              {
                "id": "2",
                "num": 30000
              },
              {
                "id": "110182",
                "num": 7
              },
              {
                "id": "114012",
                "num": 6
              }
            ]
          },
          {
            "promotion": 5,
            "level": 0,
            "properties": [],
            "materials": [
              {
                "id": "2",
                "num": 45000
              },
              {
                "id": "110183",
                "num": 3
              },
              {
                "id": "114013",
                "num": 3
              }
            ]
          },
          {
            "promotion": 5,
            "level": 0,
            "properties": [],
            "materials": [
              {
                "id": "2",
                "num": 80000
              },
              {
                "id": "110183",
                "num": 5
              },
              {
                "id": "110505",
                "num": 1
              },
              {
                "id": "114013",
                "num": 4
              }
            ]
          },
          {
            "promotion": 6,
            "level": 0,
            "properties": [],
            "materials": [
              {
                "id": "2",
                "num": 160000
              },
              {
                "id": "110183",
                "num": 8
              },
              {
                "id": "241",
                "num": 1
              },
              {
                "id": "110505",
                "num": 1
              }
            ]
          },
          {
            "promotion": 6,
            "level": 0,
            "properties": [],
            "materials": [
              {
                "id": "2",
                "num": 300000
              },
              {
                "id": "110183",
                "num": 14
              },
              {
                "id": "241",
                "num": 1
              },
              {
                "id": "110505",
                "num": 1
              }
            ]
          }
        ]
      },
      {
        "id": "11310007",
        "name": "",
        "desc": "",
        "anchor": "Point05",
        "pre_points": [],
        "level_up_skills": [
          {
            "id": "1131007",
            "num": 1
          }
        ],
        "levels": [
          {
            "promotion": 0,
            "level": 0,
            "properties": [],
            "materials": []
          }
        ]
      }
    ],
    "ability_bonuses": [
      {
        "id": "1310101",
        "name": "α模组-偏时迸发",
        "desc": "「完全燃烧」状态下，攻击没有火属性弱点的敌人也能削减韧性，效果等同于原技能削韧值的#1[i]%。",
        "anchor": "Point06",
        "pre_points": [],
        "max_level": 1,
        "levels": [
          {
            "promotion": 2,
            "level": 0,
            "properties": [],
            "materials": [
              {
                "id": "2",
                "num": 5000
              },
              {
                "id": "110181",
                "num": 3
              },
              {
                "id": "110505",
                "num": 1
              }
            ]
          }
        ]
      },
      {
        "id": "1310102",
        "name": "β模组-自限装甲",
        "desc": "「完全燃烧」状态下，当装甲「萨姆」的击破特攻大于等于#1[i]%/#2[i]%时，攻击处于弱点击破状态下的敌方目标后，会将本次攻击的削韧值转化为1次#3[i]%/#4[i]%的超击破伤害。",
        "anchor": "Point07",
        "pre_points": [],
        "max_level": 1,
        "levels": [
          {
            "promotion": 4,
            "level": 0,
            "properties": [],
            "materials": [
              {
                "id": "2",
                "num": 20000
              },
              {
                "id": "110182",
                "num": 5
              },
              {
                "id": "241",
                "num": 1
              },
              {
                "id": "110505",
                "num": 1
              }
            ]
          }
        ]
      },
      {
        "id": "1310103",
        "name": "γ模组-过载核心",
        "desc": "若装甲「萨姆」的攻击力高于#1[i]点，每超过#2[i]点攻击力可使自身击破特攻提高#3[f1]%。",
        "anchor": "Point08",
        "pre_points": [],
        "max_level": 1,
        "levels": [
          {
            "promotion": 6,
            "level": 0,
            "properties": [],
            "materials": [
              {
                "id": "2",
                "num": 160000
              },
              {
                "id": "110183",
                "num": 8
              },
              {
                "id": "241",
                "num": 1
              },
              {
                "id": "110505",
                "num": 1
              }
            ]
          }
        ]
      },
      {
        "id": "11310101",
        "name": "α模组-偏时迸发",
        "desc": "「完全燃烧」状态下，装甲「萨姆」的击破特攻提高#1[i]%，施放强化普攻、强化战技使目标陷入弱点击破状态时，「完全燃烧」倒计时行动延后#2[i]%，该效果在每次「完全燃烧」状态期间最多触发#3[i]次。",
        "anchor": "Point06",
        "pre_points": [],
        "max_level": 1,
        "levels": [
          {
            "promotion": 2,
            "level": 0,
            "properties": [],
            "materials": [
              {
                "id": "2",
                "num": 5000
              },
              {
                "id": "110181",
                "num": 3
              },
              {
                "id": "110505",
                "num": 1
              }
            ]
          }
        ]
      },
      {
        "id": "11310102",
        "name": "β模组-自限装甲",
        "desc": "「完全燃烧」状态下，当装甲「萨姆」的击破特攻大于等于#1[i]%/#2[i]%时，攻击处于弱点击破状态下的敌方目标后，会将本次攻击的削韧值转化为1次#3[i]%/#4[i]%的超击破伤害。",
        "anchor": "Point07",
        "pre_points": [],
        "max_level": 1,
        "levels": [
          {
            "promotion": 4,
            "level": 0,
            "properties": [],
            "materials": [
              {
                "id": "2",
                "num": 20000
              },
              {
                "id": "110182",
                "num": 5
              },
              {
                "id": "241",
                "num": 1
              },
              {
                "id": "110505",
                "num": 1
              }
            ]
          }
        ]
      },
      {
        "id": "11310103",
        "name": "γ模组-过载核心",
        "desc": "若装甲「萨姆」的攻击力高于#1[i]点，每超过#2[i]点攻击力可使自身击破特攻提高#3[f1]%。",
        "anchor": "Point08",
        "pre_points": [],
        "max_level": 1,
        "levels": [
          {
            "promotion": 6,
            "level": 0,
            "properties": [],
            "materials": [
              {
                "id": "2",
                "num": 160000
              },
              {
                "id": "110183",
                "num": 8
              },
              {
                "id": "241",
                "num": 1
              },
              {
                "id": "110505",
                "num": 1
              }
            ]
          }
        ]
      }
    ],
    "stat_bonuses": [
      {
        "id": "1310201",
        "name": "击破强化",
        "anchor": "Point09",
        "pre_points": [],
        "properties": [
          {
            "type": "BreakDamageAddedRatioBase",
            "name": "击破特攻",
            "value": 0.053
          }
        ]
      },
      {
        "id": "1310202",
        "name": "效果抵抗强化",
        "anchor": "Point10",
        "pre_points": [
          "1310101"
        ],
        "properties": [
          {
            "type": "StatusResistanceBase",
            "name": "效果抵抗",
            "value": 0.04
          }
        ]
      },
      {
        "id": "1310203",
        "name": "击破强化",
        "anchor": "Point11",
        "pre_points": [
          "1310202"
        ],
        "properties": [
          {
            "type": "BreakDamageAddedRatioBase",
            "name": "击破特攻",
            "value": 0.053
          }
        ]
      },
      {
        "id": "1310204",
        "name": "速度强化",
        "anchor": "Point12",
        "pre_points": [
          "1310203"
        ],
        "properties": [
          {
            "type": "SpeedDelta",
            "name": "速度",
            "value": 2
          }
        ]
      },
      {
        "id": "1310205",
        "name": "击破强化",
        "anchor": "Point13",
        "pre_points": [
          "1310102"
        ],
        "properties": [
          {
            "type": "BreakDamageAddedRatioBase",
            "name": "击破特攻",
            "value": 0.08
          }
        ]
      },
      {
        "id": "1310206",
        "name": "效果抵抗强化",
        "anchor": "Point14",
        "pre_points": [
          "1310205"
        ],
        "properties": [
          {
            "type": "StatusResistanceBase",
            "name": "效果抵抗",
            "value": 0.06
          }
        ]
      },
      {
        "id": "1310207",
        "name": "击破强化",
        "anchor": "Point15",
        "pre_points": [
          "1310206"
        ],
        "properties": [
          {
            "type": "BreakDamageAddedRatioBase",
            "name": "击破特攻",
            "value": 0.08
          }
        ]
      },
      {
        "id": "1310208",
        "name": "速度强化",
        "anchor": "Point16",
        "pre_points": [
          "1310103"
        ],
        "properties": [
          {
            "type": "SpeedDelta",
            "name": "速度",
            "value": 3
          }
        ]
      },
      {
        "id": "1310209",
        "name": "效果抵抗强化",
        "anchor": "Point17",
        "pre_points": [
          "1310208"
        ],
        "properties": [
          {
            "type": "StatusResistanceBase",
            "name": "效果抵抗",
            "value": 0.08
          }
        ]
      },
      {
        "id": "1310210",
        "name": "击破强化",
        "anchor": "Point18",
        "pre_points": [
          "1310208"
        ],
        "properties": [
          {
            "type": "BreakDamageAddedRatioBase",
            "name": "击破特攻",
            "value": 0.107
          }
        ]
      },
      {
        "id": "11310201",
        "name": "击破强化",
        "anchor": "Point09",
        "pre_points": [],
        "properties": [
          {
            "type": "BreakDamageAddedRatioBase",
            "name": "击破特攻",
            "value": 0.053
          }
        ]
      },
      {
        "id": "11310202",
        "name": "效果抵抗强化",
        "anchor": "Point10",
        "pre_points": [
          "11310101"
        ],
        "properties": [
          {
            "type": "StatusResistanceBase",
            "name": "效果抵抗",
            "value": 0.04
          }
        ]
      },
      {
        "id": "11310203",
        "name": "击破强化",
        "anchor": "Point11",
        "pre_points": [
          "11310202"
        ],
        "properties": [
          {
            "type": "BreakDamageAddedRatioBase",
            "name": "击破特攻",
            "value": 0.053
          }
        ]
      },
      {
        "id": "11310204",
        "name": "速度强化",
        "anchor": "Point12",
        "pre_points": [
          "11310203"
        ],
        "properties": [
          {
            "type": "SpeedDelta",
            "name": "速度",
            "value": 2
          }
        ]
      },
      {
        "id": "11310205",
        "name": "击破强化",
        "anchor": "Point13",
        "pre_points": [
          "11310102"
        ],
        "properties": [
          {
            "type": "BreakDamageAddedRatioBase",
            "name": "击破特攻",
            "value": 0.08
          }
        ]
      },
      {
        "id": "11310206",
        "name": "效果抵抗强化",
        "anchor": "Point14",
        "pre_points": [
          "11310205"
        ],
        "properties": [
          {
            "type": "StatusResistanceBase",
            "name": "效果抵抗",
            "value": 0.06
          }
        ]
      },
      {
        "id": "11310207",
        "name": "击破强化",
        "anchor": "Point15",
        "pre_points": [
          "11310206"
        ],
        "properties": [
          {
            "type": "BreakDamageAddedRatioBase",
            "name": "击破特攻",
            "value": 0.08
          }
        ]
      },
      {
        "id": "11310208",
        "name": "速度强化",
        "anchor": "Point16",
        "pre_points": [
          "11310103"
        ],
        "properties": [
          {
            "type": "SpeedDelta",
            "name": "速度",
            "value": 3
          }
        ]
      },
      {
        "id": "11310209",
        "name": "效果抵抗强化",
        "anchor": "Point17",
        "pre_points": [
          "11310208"
        ],
        "properties": [
          {
            "type": "StatusResistanceBase",
            "name": "效果抵抗",
            "value": 0.08
          }
        ]
      },
      {
        "id": "11310210",
        "name": "击破强化",
        "anchor": "Point18",
        "pre_points": [
          "11310208"
        ],
        "properties": [
          {
            "type": "BreakDamageAddedRatioBase",
            "name": "击破特攻",
            "value": 0.107
          }
        ]
      }
    ]
  },
  "eidolons": [
    {
      "id": "131001",
      "name": "我曾安眠，赤染之茧",
      "rank": 1,
      "desc": "施放强化战技时无视目标15%的防御，且强化战技不消耗战技点。",
      "level_up_skills": [],
      "max_level": 1
    },
    {
      "id": "131002",
      "name": "自破碎的天空坠落",
      "rank": 2,
      "desc": "「完全燃烧」状态下施放强化普攻、强化战技消灭敌方目标或使目标陷入弱点击破状态时，装甲「萨姆」立即获得1个额外回合。该效果在1回合后可再次触发。",
      "level_up_skills": [],
      "max_level": 1
    },
    {
      "id": "131003",
      "name": "沉睡在静默的星河",
      "rank": 3,
      "desc": "战技等级+2，最多不超过15级；普攻等级+1，最多不超过10级。",
      "level_up_skills": [
        {
          "id": "131002",
          "num": 2
        },
        {
          "id": "131001",
          "num": 1
        },
        {
          "id": "131009",
          "num": 2
        },
        {
          "id": "131008",
          "num": 1
        }
      ],
      "max_level": 1
    },
    {
      "id": "131004",
      "name": "我会看见，飞萤之火",
      "rank": 4,
      "desc": "「完全燃烧」状态下，装甲「萨姆」的效果抵抗提高50%。",
      "level_up_skills": [],
      "max_level": 1
    },
    {
      "id": "131005",
      "name": "自无梦的长夜亮起",
      "rank": 5,
      "desc": "终结技等级+2，最多不超过15级；天赋等级+2，最多不超过15级。",
      "level_up_skills": [
        {
          "id": "131003",
          "num": 2
        },
        {
          "id": "131004",
          "num": 2
        }
      ],
      "max_level": 1
    },
    {
      "id": "131006",
      "name": "绽放在终竟的明天",
      "rank": 6,
      "desc": "「完全燃烧」状态下装甲「萨姆」的火属性抗性穿透提高20%。施放强化普攻、强化战技时弱点击破效率提高50%。",
      "level_up_skills": [],
      "max_level": 1
    }
  ]
}